setup.py
windy/__init__.py
windy/__main__.py
windy.egg-info/PKG-INFO
windy.egg-info/SOURCES.txt
windy.egg-info/dependency_links.txt
windy.egg-info/entry_points.txt
windy.egg-info/not-zip-safe
windy.egg-info/top_level.txt
windy/gui/__init__.py
windy/gui/about.py
windy/gui/application.py
windy/gui/env_variable_editor.py
windy/gui/env_variable_import.py
windy/gui/locale.py
windy/service/__init__.py
windy/service/environment_variables_service.py