Metadata-Version: 1.1
Name: windy
Version: 0.9.8.4
Summary: windy is an application for managing Windows user/system environment variables.
Home-page: http://github.com/zeljko.m.gavrilovic/windy
Author: BigNumbers
Author-email: zeljko.m.gavrilovic@gmail.com
License: GPLv3
Keywords: windows,environment,variables,path,developer,java
Platform: UNKNOWN
Classifier: Programming Language :: Python
Classifier: Programming Language :: Python :: 3
Classifier: Development Status :: 4 - Beta
Classifier: Intended Audience :: Developers
Classifier: Intended Audience :: System Administrators
Classifier: Operating System :: Microsoft :: Windows
Classifier: Topic :: Desktop Environment
Classifier: License :: Freeware
Classifier: Topic :: Utilities
